bonky/__init__.py
bonky-0.0.1.dist-info/METADATA
bonky-0.0.1.dist-info/WHEEL
bonky-0.0.1.dist-info/top_level.txt
bonky-0.0.1.dist-info/RECORD
