Metadata-Version: 2.2
Name: bonky
Version: 0.0.1
Summary: Test
Author-email: ribbitx <mail@ribbitx.com>
License: MIT
Requires-Dist: requests
